marlowe-0.1.6.dist-info/METADATA
marlowe-0.1.6.dist-info/WHEEL
marlowe/__init__.py
marlowe/marlowe.cpython-310-darwin.so
marlowe-0.1.6.dist-info/RECORD
